{
    "Vennootschapsnaam": "MIMESYS",
    "Vennootschapsvorm": "Besloten Vennootschap",
    "Ondernemingsnummer": "0652.604.320",
    "Adres": "Kempische steenweg, 303 17, 3500, Hasselt",
    " ": "bekijk op kaart",
    "Oprichtingsakte": "Officiële Domeinnaamregistratie voor Bedrijven",
    "Laatste publicatie": "Lijst van alle staatsbladspublicaties",
    "Laatste jaarrekening": "Activiteitsgegevens verkregen onder de Gratis Open Data Licentie Vlaanderen v. 1.2",
    "url": "https://www.staatsbladmonitor.be/bedrijfsfiche.html?ondernemingsnummer=0652604320"
}