{
    "Vennootschapsnaam": "Mega-Mavzer",
    "Vennootschapsvorm": "Besloten vennootschap met beperkte aansprakelijkheid",
    "Ondernemingsnummer": "0659.909.113",
    "Adres": "Gaston Crommenlaan, 4 /501, 9050, Gent",
    " ": "bekijk op kaart",
    "Oprichtingsakte": "Officiële Domeinnaamregistratie voor Bedrijven",
    "Laatste publicatie": "Lijst van alle staatsbladspublicaties",
    "Laatste jaarrekening": "Activiteitsgegevens verkregen onder de Gratis Open Data Licentie Vlaanderen v. 1.2",
    "url": "https://www.staatsbladmonitor.be/bedrijfsfiche.html?ondernemingsnummer=0659909113"
}