{
    "Vennootschapsnaam": "Association d'Aide aux Personnes en Belgique et à l'Etranger",
    "Vennootschapsvorm": "Vereniging zonder winstoogmerk",
    "Ondernemingsnummer": "0660.651.855",
    "Adres": "Edmond Candrieslaan, 3 9, 1080, Sint-Jans-Molenbeek",
    " ": "bekijk op kaart",
    "Oprichtingsakte": "Officiële Domeinnaamregistratie voor Bedrijven",
    "Laatste publicatie": "Lijst van alle staatsbladspublicaties",
    "url": "https://www.staatsbladmonitor.be/bedrijfsfiche.html?ondernemingsnummer=0660651855"
}