{
    "Vennootschapsnaam": "European Researches and Priojects for Educational, Cultural and Social Innovation",
    "Vennootschapsvorm": "Vereniging zonder winstoogmerk",
    "Ondernemingsnummer": "0646.754.428",
    "Adres": "Margaretasquare, 42 , 1000, Brussel",
    " ": "bekijk op kaart",
    "Oprichtingsakte": "Officiële Domeinnaamregistratie voor Bedrijven",
    "Laatste publicatie": "Lijst van alle staatsbladspublicaties",
    "url": "https://www.staatsbladmonitor.be/bedrijfsfiche.html?ondernemingsnummer=0646754428"
}