{
    "Vennootschapsnaam": "WOLFOOD",
    "Vennootschapsvorm": "Besloten vennootschap met beperkte aansprakelijkheid",
    "Ondernemingsnummer": "0666.477.595",
    "Adres": "Place Maugrétout(L.L), 5 , 7100, La Louvière",
    "Oprichtingsakte": "bekijk op kaart",
    "Laatste publicatie": "Officiële Domeinnaamregistratie voor Bedrijven",
    "Laatste jaarrekening": "Lijst van alle staatsbladspublicaties",
    "url": "https://www.staatsbladmonitor.be/bedrijfsfiche.html?ondernemingsnummer=0666477595"
}