{
    "Vennootschapsnaam": "PADEK INVEST",
    "Vennootschapsvorm": "Besloten vennootschap met beperkte aansprakelijkheid",
    "Ondernemingsnummer": "0666.864.112",
    "Adres": "Hubert Heymansstraat, 1 , 1082, Sint-Agatha-Berchem",
    " ": "bekijk op kaart",
    "Oprichtingsakte": "Officiële Domeinnaamregistratie voor Bedrijven",
    "Laatste publicatie": "Lijst van alle staatsbladspublicaties",
    "Laatste jaarrekening": "niet beschikbaar",
    "url": "https://www.staatsbladmonitor.be/bedrijfsfiche.html?ondernemingsnummer=0666864112"
}