{
    "Vennootschapsnaam": "MARKETING COMMERCIAL DEVELOPPEMENT SERVICES",
    "Vennootschapsvorm": "Besloten vennootschap met beperkte aansprakelijkheid",
    "Ondernemingsnummer": "0647.750.558",
    "Adres": "El Rowe, 25 , 4550, Nandrin",
    "Oprichtingsakte": "bekijk op kaart",
    "Laatste publicatie": "Officiële Domeinnaamregistratie voor Bedrijven",
    "Laatste jaarrekening": "Lijst van alle staatsbladspublicaties",
    "url": "https://www.staatsbladmonitor.be/bedrijfsfiche.html?ondernemingsnummer=0647750558"
}