{
    "Vennootschapsnaam": "HOLDING ALEXANDRE COMMUNICATION",
    "Vennootschapsvorm": "Besloten vennootschap met beperkte aansprakelijkheid",
    "Ondernemingsnummer": "0649.887.330",
    "Adres": "Libramont,Rue du Serpont, 29A 3, 6800, Libramont-Chevigny",
    " ": "bekijk op kaart",
    "Oprichtingsakte": "Officiële Domeinnaamregistratie voor Bedrijven",
    "Laatste publicatie": "Lijst van alle staatsbladspublicaties",
    "url": "https://www.staatsbladmonitor.be/bedrijfsfiche.html?ondernemingsnummer=0649887330"
}