{
    "Généralités": {
        "Numéro d'entreprise:": "0543.710.932",
        "Statut:": "Actif",
        "Situation juridique:": "Situation normaleDepuis le 31 décembre 2013",
        "Date de début:": "31 décembre 2013",
        "Dénomination:": "DE VERZEKERINGSADVISEURSDénomination en néerlandais, depuis le 31 décembre 2013",
        "Adresse du siège:": "Hovestraat 35\n2650 Edegem\nDepuis le 31 décembre 2013",
        "Numéro de téléphone:": null,
        "Numéro de fax:": null,
        "E-mail:": null,
        "Adresse web:": null,
        "Type d'entité:": "Personne morale",
        "Forme légale:": "Société privée à responsabilité limitée\nDepuis le 31 décembre 2013",
        "Nombre d'unités d'établissement (UE):": "2 \nListe UE - Données et Activités par UE"
    },
    "Fonctions": {
        "Gérant": {
            "nom": "Vos   Dirk",
            "date": "Depuis le 31 décembre 2013"
        }
    },
    "Compétences professionnelles et connaissances de gestion de base": "",
    "Qualités": "Entreprise soumise à inscription Depuis le 1 novembre 2018",
    "Autorisations": "Connaissances de gestion de base Depuis le 13 janvier 2014",
    "Activités TVA Code Nacebel version 2008(1)": "TVA 2008 \n64.200  - \nActivités des sociétés holding Depuis le 1 août 2016",
    "Activités ONSS Code Nacebel version 2008(1)": "ONSS2008 \n66.220 - \nActivités des agents et courtiers d'assurances Depuis le 1 janvier 2018",
    "Données financières": {
        "Capital": "411.415 EUR",
        "Assemblée générale": "mai",
        "Date de fin de l'année comptable": "31 décembre"
    },
    "Liens entre entités": "0456.454.680\n \nest absorbée par cette entité \ndepuis le  11 janvier 2018",
    "Liens externes": "Liens externes"
}