{
    "Vennootschapsnaam": "EQUIPE MULTI HOSPITALIERE DE CHIRURGIE CARDIOVASCULAIRE ET THORACIQUE",
    "Vennootschapsvorm": "Economisch samenwerkingsverband",
    "Ondernemingsnummer": "0675.924.011",
    "Adres": "Rue Marguerite Depasse, 6 , 6060, Charleroi",
    " ": "bekijk op kaart",
    "Oprichtingsakte": "Officiële Domeinnaamregistratie voor Bedrijven",
    "Laatste publicatie": "Lijst van alle staatsbladspublicaties",
    "Laatste jaarrekening": "niet beschikbaar",
    "url": "https://www.staatsbladmonitor.be/bedrijfsfiche.html?ondernemingsnummer=0675924011"
}