{
    "Vennootschapsnaam": "Association des Enseignants de l'Ecole Fondamentale annexée à l'Athénée Royal de la Rive Gauche, asbl",
    "Vennootschapsvorm": "Vereniging zonder winstoogmerk",
    "Ondernemingsnummer": "0676.544.910",
    "Adres": "Maria-Christinastraat, 83 , 1020, Brussel",
    " ": "bekijk op kaart",
    "Oprichtingsakte": "Officiële Domeinnaamregistratie voor Bedrijven",
    "Laatste publicatie": "Lijst van alle staatsbladspublicaties",
    "url": "https://www.staatsbladmonitor.be/bedrijfsfiche.html?ondernemingsnummer=0676544910"
}