{
    "Vennootschapsnaam": "Association professionnelle des médecins d'orientation psychodynamique",
    "Vennootschapsvorm": "Vereniging zonder winstoogmerk",
    "Ondernemingsnummer": "0669.949.603",
    "Adres": "Gulden-Sporenlaan, 1 , 1050, Elsene",
    " ": "bekijk op kaart",
    "Oprichtingsakte": "Officiële Domeinnaamregistratie voor Bedrijven",
    "Laatste publicatie": "Lijst van alle staatsbladspublicaties",
    "url": "https://www.staatsbladmonitor.be/bedrijfsfiche.html?ondernemingsnummer=0669949603"
}