{
    "Vennootschapsnaam": "European Funeral Innovation Awards België Belgique Belgien",
    "Vennootschapsvorm": "Vereniging zonder winstoogmerk",
    "Ondernemingsnummer": "0671.630.077",
    "Adres": "Drakenhoflaan, 21 , 2100, Antwerpen",
    " ": "bekijk op kaart",
    "Oprichtingsakte": "Officiële Domeinnaamregistratie voor Bedrijven",
    "Laatste publicatie": "Lijst van alle staatsbladspublicaties",
    "url": "https://www.staatsbladmonitor.be/bedrijfsfiche.html?ondernemingsnummer=0671630077"
}