{
    "Vennootschapsnaam": "société médicale Docteur Fabian Warzée",
    "Vennootschapsvorm": "Besloten vennootschap met beperkte aansprakelijkheid",
    "Ondernemingsnummer": "0671.686.693",
    "Adres": "Rue Sainte Julienne, 8 , 4621, Fléron",
    "Oprichtingsakte": "bekijk op kaart",
    "Laatste publicatie": "Officiële Domeinnaamregistratie voor Bedrijven",
    "Laatste jaarrekening": "Lijst van alle staatsbladspublicaties",
    "url": "https://www.staatsbladmonitor.be/bedrijfsfiche.html?ondernemingsnummer=0671686693"
}