{
    "Vennootschapsnaam": "RB Horeca",
    "Vennootschapsvorm": "Besloten vennootschap met beperkte aansprakelijkheid",
    "Ondernemingsnummer": "0652.890.667",
    "Adres": "Itegemseweg(WIE), 62 , 2222, Heist-op-den-Berg",
    " ": "bekijk op kaart",
    "Oprichtingsakte": "Officiële Domeinnaamregistratie voor Bedrijven",
    "Laatste publicatie": "Lijst van alle staatsbladspublicaties",
    "Laatste jaarrekening": "Activiteitsgegevens verkregen onder de Gratis Open Data Licentie Vlaanderen v. 1.2",
    "url": "https://www.staatsbladmonitor.be/bedrijfsfiche.html?ondernemingsnummer=0652890667"
}