{
    "Vennootschapsnaam": "SCOL'AIDE, AMICALE DE L'ATHENEE ROYAL DE SAINT-GOERGES-SUR-MEUSE",
    "Vennootschapsvorm": "Vereniging zonder winstoogmerk",
    "Ondernemingsnummer": "0654.824.828",
    "Adres": "Rue Eloi Fouarge, 31 , 4470, Saint-Georges-sur-Meuse",
    " ": "bekijk op kaart",
    "Oprichtingsakte": "Officiële Domeinnaamregistratie voor Bedrijven",
    "Laatste publicatie": "Lijst van alle staatsbladspublicaties",
    "url": "https://www.staatsbladmonitor.be/bedrijfsfiche.html?ondernemingsnummer=0654824828"
}