{
    "Vennootschapsnaam": "Reno Creator",
    "Vennootschapsvorm": "Besloten vennootschap met beperkte aansprakelijkheid",
    "Ondernemingsnummer": "0657.950.010",
    "Adres": "Van Deynsestraat, 22 , 2100, Antwerpen",
    "Oprichtingsakte": "bekijk op kaart",
    "Laatste publicatie": "Officiële Domeinnaamregistratie voor Bedrijven",
    "Laatste jaarrekening": "Lijst van alle staatsbladspublicaties",
    "url": "https://www.staatsbladmonitor.be/bedrijfsfiche.html?ondernemingsnummer=0657950010"
}