{
    "Vennootschapsnaam": "Dokter Vanhooren Femke Psychiatrie",
    "Vennootschapsvorm": "Besloten vennootschap met beperkte aansprakelijkheid",
    "Ondernemingsnummer": "0661.906.719",
    "Adres": "Rosalialaan, 33 , 2650, Edegem",
    "Oprichtingsakte": "bekijk op kaart",
    "Laatste publicatie": "Officiële Domeinnaamregistratie voor Bedrijven",
    "Laatste jaarrekening": "Lijst van alle staatsbladspublicaties",
    "url": "https://www.staatsbladmonitor.be/bedrijfsfiche.html?ondernemingsnummer=0661906719"
}