{
    "Vennootschapsnaam": "AJD & Co",
    "Vennootschapsvorm": "Naamloze vennootschap",
    "Ondernemingsnummer": "0666.757.115",
    "Adres": "Rue Aux-Cailloux, Rhisnes, 34 , 5080, La Bruyère",
    " ": "bekijk op kaart",
    "Oprichtingsakte": "Officiële Domeinnaamregistratie voor Bedrijven",
    "Laatste publicatie": "Lijst van alle staatsbladspublicaties",
    "Laatste jaarrekening": "Activiteitsgegevens verkregen onder de Gratis Open Data Licentie Vlaanderen v. 1.2",
    "url": "https://www.staatsbladmonitor.be/bedrijfsfiche.html?ondernemingsnummer=0666757115"
}