{
    "Vennootschapsnaam": "VAN HOUTERT SCHROOTEN ACCOUNTANTS",
    "Vennootschapsvorm": "Besloten vennootschap met beperkte aansprakelijkheid",
    "Ondernemingsnummer": "0667.662.678",
    "Adres": "Nachtegaalstraat, 8 W8, 9240, Zele",
    " ": "bekijk op kaart",
    "Oprichtingsakte": "Officiële Domeinnaamregistratie voor Bedrijven",
    "Laatste publicatie": "Lijst van alle staatsbladspublicaties",
    "Laatste jaarrekening": "Activiteitsgegevens verkregen onder de Gratis Open Data Licentie Vlaanderen v. 1.2",
    "url": "https://www.staatsbladmonitor.be/bedrijfsfiche.html?ondernemingsnummer=0667662678"
}