{
    "Vennootschapsnaam": "TADREAMS",
    "Vennootschapsvorm": "Besloten vennootschap met beperkte aansprakelijkheid",
    "Ondernemingsnummer": "0667.831.835",
    "Adres": "Vorstse Steenweg, 42 , 1060, Sint-Gillis (bij-Brussel)",
    " ": "bekijk op kaart",
    "Oprichtingsakte": "Officiële Domeinnaamregistratie voor Bedrijven",
    "Laatste publicatie": "Lijst van alle staatsbladspublicaties",
    "Laatste jaarrekening": "Activiteitsgegevens verkregen onder de Gratis Open Data Licentie Vlaanderen v. 1.2",
    "url": "https://www.staatsbladmonitor.be/bedrijfsfiche.html?ondernemingsnummer=0667831835"
}