{
    "Vennootschapsnaam": "CLAESSENS ENDOCRINOLOGIE",
    "Vennootschapsvorm": "Besloten vennootschap met beperkte aansprakelijkheid",
    "Ondernemingsnummer": "0648.777.966",
    "Adres": "Rue des Combattants, Les Fossés, 4 , 6860, Léglise",
    "Oprichtingsakte": "bekijk op kaart",
    "Laatste publicatie": "Officiële Domeinnaamregistratie voor Bedrijven",
    "Laatste jaarrekening": "Lijst van alle staatsbladspublicaties",
    "url": "https://www.staatsbladmonitor.be/bedrijfsfiche.html?ondernemingsnummer=0648777966"
}