{
    "Vennootschapsnaam": "OXYGEN DEVELOPMENT",
    "Vennootschapsvorm": "Naamloze vennootschap",
    "Ondernemingsnummer": "0673.739.135",
    "Adres": "Gemeenschappenlaan, 100 , 1200, Sint-Lambrechts-Woluwe",
    " ": "bekijk op kaart",
    "Oprichtingsakte": "Officiële Domeinnaamregistratie voor Bedrijven",
    "Laatste publicatie": "Lijst van alle staatsbladspublicaties",
    "Laatste jaarrekening": "niet beschikbaar",
    "url": "https://www.staatsbladmonitor.be/bedrijfsfiche.html?ondernemingsnummer=0673739135"
}