{
    "Vennootschapsnaam": "MICKAËL PANCHOUT",
    "Vennootschapsvorm": "Besloten vennootschap met beperkte aansprakelijkheid",
    "Ondernemingsnummer": "0674.677.758",
    "Adres": "Rue de Henri-Chapelle,Battice, 12 , 4651, Herve",
    " ": "bekijk op kaart",
    "Oprichtingsakte": "Officiële Domeinnaamregistratie voor Bedrijven",
    "Laatste publicatie": "Lijst van alle staatsbladspublicaties",
    "Laatste jaarrekening": "niet beschikbaar",
    "url": "https://www.staatsbladmonitor.be/bedrijfsfiche.html?ondernemingsnummer=0674677758"
}