{
    "Vennootschapsnaam": "Fédération Belge de Disque Volant - Belgische Flying Disc Federatie",
    "Vennootschapsvorm": "Vereniging zonder winstoogmerk",
    "Ondernemingsnummer": "0675.411.394",
    "Adres": "Voltastraat, 18 , 1050, Elsene",
    " ": "bekijk op kaart",
    "Oprichtingsakte": "Officiële Domeinnaamregistratie voor Bedrijven",
    "Laatste publicatie": "Lijst van alle staatsbladspublicaties",
    "url": "https://www.staatsbladmonitor.be/bedrijfsfiche.html?ondernemingsnummer=0675411394"
}