{
    "Vennootschapsnaam": "ASSOCIATION POUR L'USAGE, LA DEFENSE ET LA PROMOTION DU PATE GAUMAIS ET DE SON APPELLATION",
    "Vennootschapsvorm": "Vereniging zonder winstoogmerk",
    "Ondernemingsnummer": "0463.071.268",
    "Adres": "Rue des Grasses-Oies, 2B , 6760, Virton",
    " ": "bekijk op kaart",
    "Oprichtingsakte": "Officiële Domeinnaamregistratie voor Bedrijven",
    "Laatste publicatie": "Lijst van alle staatsbladspublicaties",
    "url": "https://www.staatsbladmonitor.be/bedrijfsfiche.html?ondernemingsnummer=0463071268"
}