{
    "Vennootschapsnaam": "VINCE & CO",
    "Vennootschapsvorm": "Besloten vennootschap met beperkte aansprakelijkheid",
    "Ondernemingsnummer": "0671.855.751",
    "Adres": "Voye-d'en-Haut (VOD), 35 , 5680, Doische",
    "Oprichtingsakte": "bekijk op kaart",
    "Laatste publicatie": "Officiële Domeinnaamregistratie voor Bedrijven",
    "Laatste jaarrekening": "Lijst van alle staatsbladspublicaties",
    "url": "https://www.staatsbladmonitor.be/bedrijfsfiche.html?ondernemingsnummer=0671855751"
}