{
    "Généralités": {
        "Numéro d'entreprise:": "0543.705.586",
        "Statut:": "Actif",
        "Situation juridique:": "Situation normaleDepuis le 31 décembre 2013",
        "Date de début:": "31 décembre 2013",
        "Dénomination:": "EMOTRANS BELGIUMDénomination en français, depuis le 27 décembre 2013",
        "Adresse du siège:": "Avenue Marcel Thiry 77\n \nBoîte 4\n1200 Woluwe-Saint-Lambert\nDepuis le 27 décembre 2013",
        "Numéro de téléphone:": null,
        "Numéro de fax:": null,
        "E-mail:": null,
        "Adresse web:": null,
        "Type d'entité:": "Personne morale",
        "Forme légale:": "Société anonyme\nDepuis le 27 décembre 2013",
        "Nombre d'unités d'établissement (UE):": "1 \nDonnées et Activités par UE"
    },
    "Fonctions": {
        "Administrateur délégué": {
            "nom": "RICHTER   JEAN MARC",
            "date": "Depuis le 20 avril 2016"
        }
    },
    "Compétences professionnelles et connaissances de gestion de base": "",
    "Qualités": "Entreprise soumise à inscription Depuis le 1 novembre 2018",
    "Autorisations": "Connaissances de gestion de base Depuis le 15 février 2014",
    "Activités TVA Code Nacebel version 2008(1)": "TVA 2008 \n52.290  - \nAutres services auxiliaires des transports Depuis le 15 février 2014",
    "Activités ONSS Code Nacebel version 2008(1)": "ONSS2008 \n52.290 - \nAutres services auxiliaires des transports Depuis le 14 février 2014",
    "Données financières": {
        "Capital": "91.000 EUR",
        "Assemblée générale": "juin",
        "Date de fin de l'année comptable": "31 décembre"
    },
    "Liens entre entités": "Pas de données reprises dans la BCE.",
    "Liens externes": "Liens externes"
}