{
    "Généralités": {
        "Numéro d'entreprise:": "0543.650.851",
        "Statut:": "Actif",
        "Situation juridique:": "Situation normaleDepuis le 30 décembre 2013",
        "Date de début:": "30 décembre 2013",
        "Dénomination:": "OCEAN GROUPDénomination en français, depuis le 27 décembre 2013",
        "Adresse du siège:": "Rue de Livourne 7\n \nBoîte 4\n1060 Saint-Gilles\nDepuis le 27 décembre 2013",
        "Numéro de téléphone:": null,
        "Numéro de fax:": null,
        "E-mail:": null,
        "Adresse web:": null,
        "Type d'entité:": "Personne morale",
        "Forme légale:": "Société anonyme\nDepuis le 27 décembre 2013",
        "Nombre d'unités d'établissement (UE):": "1 \nDonnées et Activités par UE"
    },
    "Fonctions": {
        "Administrateur délégué": {
            "nom": "Essebag   Jacques",
            "date": "Depuis le 27 décembre 2013"
        }
    },
    "Compétences professionnelles et connaissances de gestion de base": "",
    "Qualités": "Entreprise soumise à inscription Depuis le 1 novembre 2018",
    "Autorisations": "Connaissances de gestion de base Depuis le 16 janvier 2014",
    "Activités TVA Code Nacebel version 2008(1)": "TVA 2008 \n59.130  - \nDistribution de films cinématographiques, de vidéo et de programmes de télévision Depuis le 1 janvier 2014",
    "Données financières": {
        "Capital": "62.000 EUR",
        "Assemblée générale": "juin",
        "Date de fin de l'année comptable": "31 décembre"
    },
    "Liens entre entités": "Pas de données reprises dans la BCE.",
    "Liens externes": "Liens externes"
}