{
    "Généralités": {
        "Numéro d'entreprise:": "0543.633.332",
        "Statut:": "Actif",
        "Situation juridique:": "Situation normaleDepuis le 23 décembre 2013",
        "Date de début:": "23 décembre 2013",
        "Dénomination:": "EDENGREEN ConsultingDénomination en français, depuis le 23 décembre 2013",
        "Adresse du siège:": "Chemin du Bonnier 10\n1380 Lasne\nDepuis le 1 mars 2016",
        "Numéro de téléphone:": null,
        "Numéro de fax:": null,
        "E-mail:": null,
        "Adresse web:": null,
        "Type d'entité:": "Personne morale",
        "Forme légale:": "Société privée à responsabilité limitée\nDepuis le 23 décembre 2013",
        "Nombre d'unités d'établissement (UE):": "1 \nDonnées et Activités par UE"
    },
    "Fonctions": {
        "Gérant": {
            "nom": "Desmet   Thierry",
            "date": "Depuis le 23 décembre 2013"
        }
    },
    "Compétences professionnelles et connaissances de gestion de base": "",
    "Qualités": "Entreprise soumise à inscription Depuis le 1 novembre 2018",
    "Autorisations": "Connaissances de gestion de base Depuis le 22 janvier 2014",
    "Activités TVA Code Nacebel version 2008(1)": "TVA 2008 \n71.113  - \nActivités d'architecture d'urbanisme, de paysage et de jardin Depuis le 23 décembre 2013",
    "Données financières": {
        "Capital": "18.550 EUR",
        "Assemblée générale": "juin",
        "Date de fin de l'année comptable": "31 décembre"
    },
    "Liens entre entités": "Pas de données reprises dans la BCE.",
    "Liens externes": "Liens externes"
}