{
    "Vennootschapsnaam": "LANDSCHAPSENERGIE",
    "Vennootschapsvorm": "Coöperatieve vennootschap met beperkte aansprakelijkheid met een sociaal oogmerk",
    "Ondernemingsnummer": "0552.573.564",
    "Adres": "Kaulillerweg, 3 , 3950, Bocholt",
    " ": "bekijk op kaart",
    "Oprichtingsakte": "Officiële Domeinnaamregistratie voor Bedrijven",
    "Laatste publicatie": "Lijst van alle staatsbladspublicaties",
    "Laatste jaarrekening": "niet beschikbaar",
    "url": "https://www.staatsbladmonitor.be/bedrijfsfiche.html?ondernemingsnummer=0552573564"
}