{
    "Vennootschapsnaam": "BY J & J",
    "Vennootschapsvorm": "Coöperatieve vennootschap met beperkte aansprakelijkheid",
    "Ondernemingsnummer": "0552.889.706",
    "Adres": "Cordoeaniersstraat, 4 , 8000, Brugge",
    "Oprichtingsakte": "bekijk op kaart",
    "Laatste publicatie": "Officiële Domeinnaamregistratie voor Bedrijven",
    "Laatste jaarrekening": "Lijst van alle staatsbladspublicaties",
    "url": "https://www.staatsbladmonitor.be/bedrijfsfiche.html?ondernemingsnummer=0552889706"
}