{
    "Vennootschapsnaam": "METHODES ET TECHNIQUES D'USINAGE",
    "Vennootschapsvorm": "Besloten vennootschap met beperkte aansprakelijkheid",
    "Ondernemingsnummer": "0553.895.140",
    "Adres": "Rue du Pont Bleu(SL), 21 , 7730, Estaimpuis",
    "Oprichtingsakte": "bekijk op kaart",
    "Laatste publicatie": "Officiële Domeinnaamregistratie voor Bedrijven",
    "Laatste jaarrekening": "Lijst van alle staatsbladspublicaties",
    "url": "https://www.staatsbladmonitor.be/bedrijfsfiche.html?ondernemingsnummer=0553895140"
}