{
    "Vennootschapsnaam": "MEDOR",
    "Vennootschapsvorm": "Coöperatieve vennootschap met beperkte aansprakelijkheid met een sociaal oogmerk",
    "Ondernemingsnummer": "0555.681.227",
    "Adres": "Rue Lamarck, 9 , 4000, Liège",
    "Oprichtingsakte": "bekijk op kaart",
    "Laatste publicatie": "Officiële Domeinnaamregistratie voor Bedrijven",
    "Laatste jaarrekening": "Lijst van alle staatsbladspublicaties",
    "url": "https://www.staatsbladmonitor.be/bedrijfsfiche.html?ondernemingsnummer=0555681227"
}