{
    "Vennootschapsnaam": "ATENEO REPUBLICANO ESPANOL EN BELGICA",
    "Vennootschapsvorm": "Vereniging zonder winstoogmerk",
    "Ondernemingsnummer": "0555.701.023",
    "Adres": "Maurice Van Meenenplein, 22 1, 1060, Sint-Gillis (bij-Brussel)",
    " ": "bekijk op kaart",
    "Oprichtingsakte": "Officiële Domeinnaamregistratie voor Bedrijven",
    "Laatste publicatie": "Lijst van alle staatsbladspublicaties",
    "url": "https://www.staatsbladmonitor.be/bedrijfsfiche.html?ondernemingsnummer=0555701023"
}