{
    "Vennootschapsnaam": "DR. K. FABRY & DR. A. VANDER AUWERA",
    "Vennootschapsvorm": "Besloten vennootschap met beperkte aansprakelijkheid",
    "Ondernemingsnummer": "0560.855.186",
    "Adres": "Marcel De Ridderstraat, 39 , 2531, Boechout",
    "Oprichtingsakte": "bekijk op kaart",
    "Laatste publicatie": "Officiële Domeinnaamregistratie voor Bedrijven",
    "Laatste jaarrekening": "Lijst van alle staatsbladspublicaties",
    "url": "https://www.staatsbladmonitor.be/bedrijfsfiche.html?ondernemingsnummer=0560855186"
}