{
    "Vennootschapsnaam": "JACOBS ANDRE ADVIES EN CONSULTING",
    "Vennootschapsvorm": "Besloten vennootschap met beperkte aansprakelijkheid",
    "Ondernemingsnummer": "0543.421.219",
    "Adres": "Ligneuville-Chemin Thomas, 20 1, 4960, Malmedy",
    "Oprichtingsakte": "bekijk op kaart",
    "Laatste publicatie": "Officiële Domeinnaamregistratie voor Bedrijven",
    "Laatste jaarrekening": "Lijst van alle staatsbladspublicaties",
    "url": "https://www.staatsbladmonitor.be/bedrijfsfiche.html?ondernemingsnummer=0543421219"
}